{
  "378": "Mercy College/Sydney Rd #39",
  "398": "Armadale St/Wattletree Rd #41",
  "409": "Kooyong Rd/Wattletree Rd #42",
  "940": "Egerton Rd/Wattletree Rd #43",
  "946": "Duncraig Ave/Wattletree Rd #44",
  "947": "Glenferrie Rd/Wattletree Rd #45",
  "950": "Nicholls St/Wattletree Rd #46",
  "955": "Cabrini Hospital/Wattletree Rd #47",
  "968": "Dixon St/Wattletree Rd #48",
  "980": "Tooronga Rd/Wattletree Rd #49",
  "992": "Maribyrnong Park/Maribyrnong Rd #41",
  "1083": "Clyde St/Raleigh Rd #42",
  "1185": "Vincent St/Wattletree Rd #50",
  "1291": "Erica Ave/Wattletree Rd #51",
  "1292": "Renown St/Sydney Rd #38",
  "1575": "Burke Rd/Wattletree Rd #52",
  "1696": "Nott St/Wattletree Rd #51",
  "1784": "Gaffney St/Sydney Rd #37",
  "1789": "Anderson St/Wattletree Rd #50",
  "2113": "Rogers St/Sydney Rd #36",
  "2232": "Tooronga Rd/Wattletree Rd #49",
  "4039": "Dorcas St/Clarendon St #128",
  "4084": "Park St/Clarendon St #129",
  "4124": "York St/Clarendon St #127",
  "4125": "City Rd/Clarendon St #126",
  "4126": "Raglan St/Clarendon St #130a",
  "4127": "Clarendon St/Albert Rd #130",
  "4128": "Melbourne Sports & Aquatic Centre/Albert Rd #131",
  "4129": "Kerferd Rd/Canterbury Rd #132",
  "4130": "Canterbury Rd/Mills St #133",
  "4131": "Carter St/Mills St #134",
  "4132": "Richardson St/Mills St #135",
  "4133": "Mills St/Danks St #136",
  "4134": "Harold St/Danks St #137",
  "4135": "Fitzroy St/Park St #143",
  "4136": "Mary St/Park St #142",
  "4137": "Deakin St/Park St #141",
  "4138": "Fraser St/Park St #140",
  "4139": "Langridge St/Patterson St #139",
  "4140": "Armstrong St/Danks St #138",
  "4141": "Gertrude St/Brunswick St #13",
  "4142": "Hanover St/Brunswick St #14",
  "4143": "Bell St/Brunswick St #15",
  "4144": "Johnston St/Brunswick St #16",
  "4145": "Leicester St/Brunswick St #17",
  "4146": "Alexandra Pde/Brunswick St #18",
  "4147": "Newry St/Brunswick St #19",
  "4148": "Fitzroy Bowls Club/Brunswick St #20",
  "4149": "Alfred Cres/St Georges Rd #21",
  "4150": "Scotchmer St/St Georges Rd #22",
  "4151": "Park St/St Georges Rd #23",
  "4152": "Holden St/St Georges Rd #24",
  "4153": "Miller St/St Georges Rd #25",
  "4154": "Clarke St/St Georges Rd #26",
  "4155": "Westbourne Gr/St Georges Rd #27",
  "4156": "Sumner Ave/St Georges Rd #28",
  "4157": "Arthurton Rd/St Georges Rd #29",
  "4158": "Gladstone Ave/St Georges Rd #30",
  "4159": "Bird Ave/St Georges Rd #31",
  "4160": "Normanby Ave/St Georges Rd #32",
  "4161": "Hutton St/St Georges Rd #33",
  "4162": "Miller St/St Georges Rd #34",
  "4163": "Bracken Ave/Miller St #36",
  "4164": "Miller St/Gilbert Rd #37",
  "4165": "Oakover Rd/Gilbert Rd #38",
  "4166": "Latona Ave/Gilbert Rd #39",
  "4167": "Bell St/Gilbert Rd #40",
  "4168": "Bruce St/Gilbert Rd #41",
  "4169": "Cramer St/Gilbert Rd #42",
  "4170": "Murray Rd/Gilbert Rd #43",
  "4171": "Cooper St/Gilbert Rd #44",
  "4172": "Jacka St/Gilbert Rd #45",
  "4173": "McNamara St/Gilbert Rd #46",
  "4174": "RMIT/Plenty Rd #71",
  "4175": "Clements Dr/Plenty Rd #70",
  "4176": "Taunton Dr/Plenty Rd #69",
  "4177": "Greenhills Rd/Plenty Rd #68",
  "4178": "Bundoora Square SC/Plenty Rd #67",
  "4179": "Settlement Rd/Plenty Rd #66",
  "4180": "Grimshaw St/Plenty Rd #65",
  "4181": "Mount Cooper Dr/Plenty Rd #64",
  "4182": "Greenwood Dr/Plenty Rd #63",
  "4183": "Metropolitan Fire Brigade/Plenty Rd #62",
  "4185": "Bundoora Park/Plenty Rd #61",
  "4186": "La Trobe University/Plenty Rd #60",
  "4187": "Preston Cemetery/Plenty Rd #59",
  "4188": "Browning St/Plenty Rd #58",
  "4189": "Reservoir District Secondary College/Plenty Rd #57",
  "4190": "Loddon Ave/Plenty Rd #56",
  "4191": "Boldrewood Pde/Plenty Rd #55",
  "4192": "Wilkinson St/Plenty Rd #54",
  "4193": "Ethel Gr/Plenty Rd #53",
  "4195": "Wood St/Plenty Rd #51",
  "4196": "Sylvester Gr/Plenty Rd #50",
  "4197": "Murray Rd/Plenty Rd #49",
  "4198": "Gower St/Plenty Rd #48",
  "4199": "David St/Plenty Rd #47",
  "4201": "Bell St/Plenty Rd #45",
  "4202": "Seymour St/Plenty Rd #44",
  "4203": "Raglan St/Plenty Rd #43",
  "4204": "Miller St/High St #42",
  "4205": "Blythe St/High St #41",
  "4206": "Mansfield St/High St #40",
  "4323": "York St/Clarendon St #127",
  "4324": "City Rd/Clarendon St #126",
  "4331": "Dorcas St/Clarendon St #128",
  "4332": "Park St/Clarendon St #129",
  "4333": "Albert Rd/Clarendon St #130",
  "4334": "Melbourne Sports & Aquatic Centre/Albert Rd #131",
  "4384": "Canterbury Rd/Albert Rd #132",
  "4440": "Canterbury Rd/Mills St #133",
  "4441": "Carter St/Mills St #134",
  "4442": "Richardson St/Mills St #135",
  "4443": "Danks St/Mills St #136",
  "4444": "Harold St/Danks St #137",
  "4445": "Mary St/Park St #142",
  "4446": "Cowderoy St/Park St #141",
  "4447": "Fraser St/Patterson St #140",
  "4448": "Langridge St/Patterson St #139",
  "4449": "Armstrong St/Danks St #138",
  "4450": "Gertrude St/Brunswick St #13",
  "4451": "King William St/Brunswick St #14",
  "4452": "St David St/Brunswick St #15",
  "4453": "Johnston St/Brunswick St #16",
  "4454": "Leicester St/Brunswick St #17",
  "4455": "Alexandra Pde/Brunswick St #18",
  "4456": "Newry St/Brunswick St #19",
  "4457": "Fitzroy Bowls Club/Brunswick St #20",
  "4458": "Alfred Cres/St Georges Rd #21",
  "4460": "Park St/St Georges Rd #23",
  "4461": "Holden St/St Georges Rd #24",
  "4462": "Miller St/St Georges Rd #25",
  "4463": "Clarke St/St Georges Rd #26",
  "4464": "Westbourne Gr/St Georges Rd #27",
  "4465": "Sumner Ave/St Georges Rd #28",
  "4466": "Arthurton Rd/St Georges Rd #29",
  "4468": "Gladstone Ave/St Georges Rd #30",
  "4469": "Gadd St/St Georges Rd #31",
  "4470": "Normanby Ave/St Georges Rd #32",
  "4471": "Hutton St/St Georges Rd #33",
  "4472": "Miller St/St Georges Rd #34",
  "4473": "Devon St/Miller St #36",
  "4474": "St Georges Rd/Miller St #35",
  "4475": "Miller St/Gilbert Rd #37",
  "4476": "Oakover Rd/Gilbert Rd #38",
  "4477": "Latona Ave/Gilbert Rd #39",
  "4478": "Bell St/Gilbert Rd #40",
  "4479": "Bruce St/Gilbert Rd #41",
  "4480": "Cramer St/Gilbert Rd #42",
  "4481": "Murray Rd/Gilbert Rd #43",
  "4482": "Cooper St/Gilbert Rd #44",
  "4483": "Jacka St/Gilbert Rd #45",
  "4484": "West Preston/Gilbert Rd #47",
  "4485": "Janefield Dr/Plenty Rd #70",
  "4486": "Taunton Dr/Plenty Rd #69",
  "4487": "Greenhills Rd/Plenty Rd #68",
  "4488": "Bundoora Square SC/Plenty Rd #67",
  "4489": "Settlement Rd/Plenty Rd #66",
  "4490": "Grimshaw St/Plenty Rd #65",
  "4491": "Mount Cooper Dr/Plenty Rd #64",
  "4492": "Greenwood Dr/Plenty Rd #63",
  "4493": "Metropolitan Fire Brigade/Plenty Rd #62",
  "4494": "Bundoora Park/Plenty Rd #61",
  "4495": "La Trobe University/Plenty Rd #60",
  "4496": "Preston Cemetery/Plenty Rd #59",
  "4497": "Browning St/Plenty Rd #58",
  "4498": "Reservoir District Secondary College/Plenty Rd #57",
  "4499": "Loddon Ave/Plenty Rd #56",
  "4500": "Albert St/Plenty Rd #55",
  "4501": "Wilkinson St/Plenty Rd #54",
  "4502": "Ethel Gr/Plenty Rd #53",
  "4503": "Tyler St/Plenty Rd #52",
  "4504": "Wood St/Plenty Rd #51",
  "4505": "Sylvester Gr/Plenty Rd #50",
  "4506": "Murray Rd/Plenty Rd #49",
  "4507": "Gower St/Plenty Rd #48",
  "4508": "David St/Plenty Rd #47",
  "4510": "Bell St/Plenty Rd #45",
  "4511": "Osborne Gr/Plenty Rd #44",
  "4512": "Raglan St/Plenty Rd #43",
  "4945": "Van Ness Ave/Raleigh Rd #43",
  "6032": "Ballantyne St/High St #39",
  "6034": "Woolton Ave/High St #37",
  "6035": "Darebin Rd/High St #36",
  "6036": "Dennis St/High St #35",
  "6037": "Bent St/High St #34",
  "6038": "Arthurton Rd/High St #33",
  "6039": "Mitchell St/High St #32",
  "6040": "Northcote Town Hall/High St #31",
  "6041": "Clarke St/High St #30",
  "6044": "Westgarth St/High St #27",
  "6045": "Walker St/High St #26",
  "6046": "Clifton Hill Interchange/Queens Pde #25",
  "6047": "Michael St/Queens Pde #24",
  "6048": "Wellington St/Queens Pde #23",
  "6049": "Smith St/Queens Pde #22",
  "6050": "Alexandra Pde/Smith St #21",
  "6051": "Rose St/Smith St #20",
  "6052": "Johnston St/Smith St #19",
  "6053": "Hodgson St/Smith St #18",
  "6054": "Charles St/Smith St #17",
  "6056": "Smith St/Gertrude St #15",
  "6057": "Napier St/Gertrude St #14",
  "6058": "Brunswick St/Gertrude St #13",
  "6059": "Moor St/Nicholson St #12",
  "6061": "Johnston St/Nicholson St #13",
  "6062": "Rose St/Nicholson St #14",
  "6063": "Alexandra Pde/Nicholson St #15",
  "6064": "Freeman St/Nicholson St #16",
  "6066": "Reid St/Nicholson St #17",
  "6067": "Scotchmer St/Nicholson St #18",
  "6068": "Holden St/Nicholson St #19",
  "6069": "Miller St/Nicholson St #20",
  "6070": "Glenlyon Rd/Nicholson St #21",
  "6071": "Albert St/Nicholson St #22",
  "6103": "Dundas St/Plenty Rd #42",
  "6104": "Collins St/High St #41",
  "6105": "Mansfield St/High St #40",
  "6106": "Gooch St/High St #39",
  "6107": "Clarendon St/High St #38",
  "6108": "Woolton Ave/High St #37",
  "6109": "Darebin Rd/High St #36",
  "6110": "Dennis St/High St #35",
  "6111": "McCutcheon St/High St #34",
  "6112": "Separation St/High St #33",
  "6113": "Mitchell St/High St #32",
  "6114": "Northcote Town Hall/High St #31",
  "6115": "Clarke St/High St #30",
  "6118": "Westgarth St/High St #27",
  "6119": "Walker St/High St #26",
  "6120": "Clifton Hill Interchange/Queens Pde #25",
  "6121": "Gold St/Queens Pde #24",
  "6122": "Wellington St/Queens Pde #23",
  "6123": "Smith St/Queens Pde #22",
  "6124": "Alexandra Pde/Smith St #21",
  "6125": "Keele St/Smith St #20",
  "6126": "Johnston St/Smith St #19",
  "6127": "Hodgson St/Smith St #18",
  "6128": "Charles St/Smith St #17",
  "6129": "Peel St/Smith St #16",
  "6130": "Gertrude St/Smith St #15",
  "6131": "Napier St/Gertrude St #14",
  "6132": "Brunswick St/Gertrude St #13",
  "6133": "Moor St/Nicholson St #12",
  "6135": "Johnston St/Nicholson St #13",
  "6136": "Rose St/Nicholson St #14",
  "6137": "Alexandra Pde/Nicholson St #15",
  "6138": "Freeman St/Nicholson St #16",
  "6140": "Reid St/Nicholson St #17",
  "6141": "Scotchmer St/Nicholson St #18",
  "6142": "Brunswick Rd/Nicholson St #19",
  "6143": "Miller St/Nicholson St #20",
  "6144": "Glenlyon Rd/Nicholson St #21",
  "6145": "Albert St/Nicholson St #22",
  "6147": "Blyth St/Nicholson St #23",
  "7354": "Dixon St/Wattletree Rd #48",
  "8345": "Cabrini Hospital/Wattletree Rd #47",
  "9156": "Soudan St/Wattletree Rd #46",
  "10311": "Glenferrie Rd/Wattletree Rd #45",
  "10371": "Duncraig Ave/Wattletree Rd #44",
  "11285": "Egerton Rd/Wattletree Rd #43",
  "12599": "Kooyong Rd/Wattletree Rd #42",
  "13401": "Punt Rd/High St #28",
  "13995": "Barb St/Raleigh Rd #44",
  "14033": "Perth St/High St #29",
  "14614": "Prahran Station/High St #30",
  "14728": "Chapel St/High St #31",
  "15559": "Randall St/Raleigh Rd #45",
  "15699": "Hornby St/High St #32",
  "16610": "Prahran RSL/High St  #33",
  "16713": "Bell St/Sydney Rd #34",
  "16714": "Coburg Market/Sydney Rd #33",
  "16715": "Munro St/Sydney Rd #32",
  "16716": "Reynard St/Sydney Rd #31",
  "16717": "The Avenue/Sydney Rd #30",
  "16718": "Lewisham Rd/High St #34",
  "16719": "Moreland Rd/Sydney Rd #28",
  "16720": "Brunswick Tram Depot/Sydney Rd #27",
  "16721": "Albion St/Sydney Rd #26",
  "16722": "Stewart St/Sydney Rd #25",
  "16723": "Brunswick Baptist Church/Sydney Rd #24",
  "16724": "Victoria St/Sydney Rd #23",
  "16725": "Albert St/Sydney Rd #22",
  "16726": "Brunswick Town Hall/Sydney Rd #21",
  "16727": "Barkly Square/Sydney Rd #20",
  "16728": "Brunswick Rd/Sydney Rd #19",
  "16730": "Ievers St/Royal Pde #17",
  "16731": "Visy Park/Royal Pde #16",
  "16732": "Leonard St/Royal Pde #15",
  "16733": "Macarthur Rd/Royal Pde #14",
  "16734": "Gatehouse St/Royal Pde #13",
  "16735": "Morrah St/Royal Pde #12",
  "16738": "Williams Rd/High St #35",
  "16739": "Chatsworth Rd/High St #36",
  "16740": "Airlie Ave/High St #37",
  "16741": "Orrong Rd/High St #38",
  "16742": "Auburn Gr/High St #39",
  "16743": "Armadale Station/High St #40",
  "16744": "Kooyong Rd/High St #41",
  "16745": "Huntingtower Rd/High St #42",
  "16746": "Mercer Rd/High St #43",
  "16747": "Glenferrie Rd/High St #44",
  "16748": "De La Salle College/High St #45",
  "16749": "Fraser St/High St #46",
  "16750": "Dixon St/High St #47",
  "16751": "Tooronga Rd/High St #48",
  "16752": "Harold Holt Swim Centre/High St #49",
  "16753": "Belmont Ave/High St #50",
  "16754": "Burke Rd/High St #51",
  "16755": "Boyanda Rd/High St #52",
  "16757": "Malvern Rd/High St #53",
  "16758": "Boyanda Rd/High St #52",
  "16759": "Burke Rd/High St #51",
  "16760": "Belmont Ave/High St #50",
  "16761": "Harold Holt Swim Centre/High St #49",
  "16762": "Tooronga Rd/High St #48",
  "16764": "Dixon St/High St #47",
  "16765": "Fraser St/High St #46",
  "16766": "De La Salle College/High St #45",
  "16767": "Glenferrie Rd/High St #44",
  "16768": "Mercer Rd/High St #43",
  "16769": "Huntingtower Rd/High St #42",
  "16770": "Kooyong Rd/High St #41",
  "16771": "Armadale Station/High St #40",
  "16772": "Auburn Gr/High St #39",
  "16773": "Orrong Rd/High St #38",
  "16774": "Airlie Ave/High St #37",
  "16775": "Chatsworth Rd/High St #36",
  "16776": "Williams Rd/High St #35",
  "16777": "Lewisham Rd/High St #34",
  "16778": "Prahran RSL/High St  #33",
  "17306": "North Coburg Terminus/Sydney Rd #40",
  "17307": "Mercy College/Sydney Rd #39",
  "17308": "Carr St/Sydney Rd #38",
  "17309": "Gaffney St/Sydney Rd #37",
  "17310": "Rogers St/Sydney Rd #36",
  "17311": "St Pauls Catholic Church/Sydney Rd #35",
  "17312": "Bell St/Sydney Rd #34",
  "17313": "Coburg Market/Sydney Rd #33",
  "17314": "Harding St/Sydney Rd #32",
  "17315": "Edward St/Sydney Rd #31",
  "17316": "The Avenue/Sydney Rd #30",
  "17317": "Moore St/Sydney Rd #29",
  "17318": "Moreland Rd/Sydney Rd #28",
  "17319": "Brunswick Tram Depot/Sydney Rd #27",
  "17320": "Albion St/Sydney Rd #26",
  "17321": "Stewart St/Sydney Rd #25",
  "17322": "Blyth St/Sydney Rd #24",
  "17323": "Victoria St/Sydney Rd #23",
  "17324": "Albert St/Sydney Rd #22",
  "17325": "Glenlyon Rd/Sydney Rd #21",
  "17327": "Brunswick Rd/Sydney Rd #19",
  "17329": "Ievers St/Royal Pde #17",
  "17330": "Walker St/Royal Pde #16",
  "17331": "Leonard St/Royal Pde #15",
  "17332": "Cemetery Road West/Royal Pde #14",
  "17333": "Gatehouse St/Royal Pde #13",
  "17334": "Morrah St/Royal Pde #12",
  "17591": "Russell St/Bourke St #7",
  "17593": "Swanston St/Bourke St #6",
  "17594": "Elizabeth St/Bourke St #5",
  "17596": "Queen St/Bourke St #4",
  "17597": "William St/Bourke St #3",
  "17602": "Hornby St/High St #32",
  "17603": "Chapel St/High St #31",
  "17604": "Prahran Station/High St #30",
  "17605": "Perth St/High St #29",
  "17606": "Punt Rd/High St #28",
  "17848": "Spencer St/Bourke St #1",
  "17849": "Spencer St/Bourke St #1",
  "17850": "Flinders Street Railway Station/Elizabeth St #1",
  "17851": "Collins St/Elizabeth St #2",
  "17852": "Bourke Street Mall/Elizabeth St #3",
  "17854": "Melbourne Central Station/Elizabeth St #5",
  "17856": "Queen Victoria Market/Elizabeth St #7",
  "17857": "Peel St/Victoria St #8",
  "17858": "William St/Victoria St #9",
  "17859": "Chetwynd St/Victoria St #10",
  "17860": "Errol St/Victoria St #11",
  "17861": "Victoria St/Errol St #11",
  "17862": "Chetwynd St/Victoria St #10",
  "17863": "Howard St/Victoria St #9",
  "17864": "Peel St/Victoria St #8",
  "17866": "Pelham St/Elizabeth St #9",
  "17867": "Royal Melbourne Hospital-Parkville Station/Royal Pde (Melbo... #10",
  "17868": "Royal Melbourne Hospital-Parkville Station/Royal Pde (Parkv... #10",
  "17869": "Pelham St/Elizabeth St #9",
  "17871": "Queen Victoria Market/Elizabeth St #7",
  "17873": "Melbourne Central Station/Elizabeth St #5",
  "17875": "Bourke Street Mall/Elizabeth St #3",
  "17876": "Collins St/Elizabeth St #2",
  "17877": "Flinders Street Railway Station/Elizabeth St #1",
  "17878": "Melbourne Museum/Nicholson St #11",
  "17880": "Albert St/Nicholson St #10",
  "17882": "Spring St/Bourke St #9",
  "17885": "William St/Bourke St #3",
  "17886": "Queen St/Bourke St #4",
  "17887": "Elizabeth St/Bourke St #5",
  "17888": "Swanston St/Bourke St #6",
  "17889": "Russell St/Bourke St #7",
  "17891": "Spring St/Bourke St #9",
  "17892": "Albert St/Nicholson St #10",
  "17894": "Melbourne Museum/Nicholson St #11",
  "17895": "St Vincents Plaza/Victoria Pde #12",
  "17896": "Albert St/Gisborne St #11",
  "17897": "Parliament Railway Station/Macarthur St #10",
  "17898": "Spring St/Collins St #8",
  "17901": "Melbourne Town Hall/Collins St #6",
  "17902": "Elizabeth St/Collins St #5",
  "17903": "William St/Collins St #3",
  "17905": "Spencer St/Collins St #1",
  "17906": "Spencer St/Collins St #1",
  "17908": "William St/Collins St #3",
  "17910": "Elizabeth St/Collins St #5",
  "17911": "Melbourne Town Hall/Collins St #6",
  "17914": "Spring St/Collins St #8",
  "17915": "Parliament Railway Station/Macarthur St #10",
  "17917": "Rosamond Rd/Raleigh Rd #46",
  "17918": "Raleigh Rd/Wests Rd #48",
  "17919": "Highpoint Shopping Centre/Wests Rd #49",
  "17920": "Wests Rd/Williamson Rd #50",
  "17921": "Williamson Rd/Rosamond Rd #51",
  "17922": "Rosamond Rd/River St #52",
  "17923": "Maribyrnong College/River St #53",
  "17924": "Gordon St/River St #54",
  "17925": "Lyric St/Gordon St #55",
  "17926": "Edgewater Square/Gordon St #56",
  "17927": "Titch St/Gordon St #57",
  "17928": "Ballarat Rd/Gordon St #58",
  "17929": "Droop St/Ballarat Rd #59",
  "17930": "Tiernan St/Droop St #60",
  "17931": "Geelong Rd/Droop St #61",
  "17932": "Nicholson St/Hopkins St #62",
  "17933": "Footscray Market/Leeds St #63",
  "17934": "Footscray Station/Leeds St #64",
  "17935": "Epsom Rd/Maribyrnong Rd #40",
  "17936": "Bowen St/Maribyrnong Rd #39",
  "17937": "Hotham St/Maribyrnong Rd #38",
  "17938": "Union Rd/Maribyrnong Rd #37",
  "17940": "Moore St/Maribyrnong Rd #35",
  "17941": "Ascot Vale Rd/Maribyrnong Rd #34",
  "17942": "Chaucer St/Ascot Vale Rd #33",
  "17944": "Central Park Ave/Cordite Ave #49",
  "17945": "St Leonards Rd/Union Rd #36",
  "17946": "Bloomfield Rd/Union Rd #35",
  "17948": "Melbourne Showgrounds/Union Rd #33",
  "17949": "Sandown Rd/Epsom Rd #32",
  "17950": "Racing Victoria/Epsom Rd #31",
  "17951": "Flemington Racecourse/Epsom Rd #30",
  "17952": "Flemington Racecourse/Racecourse Rd #29",
  "17953": "Smithfield Rd/Racecourse Rd #28",
  "17954": "Newmarket Plaza/Racecourse Rd #26",
  "17955": "Wellington St/Racecourse Rd #25",
  "17956": "Victoria St/Racecourse Rd #24",
  "17957": "Stubbs St/Racecourse Rd #23",
  "17958": "Boundary Rd/Racecourse Rd #22",
  "17959": "Melrose St/Flemington Rd #20",
  "17961": "Abbotsford St Interchange/Abbotsford St #19",
  "18006": "Albert St/Gisborne St #11",
  "18009": "Nicholson St/Victoria Pde #10",
  "18010": "La Trobe St/Victoria St #9",
  "18030": "Melbourne Central & State Library stations/La Trobe St (Melb... #6",
  "18033": "Flagstaff Station/La Trobe St  #3",
  "18037": "New Quay Prom/Docklands Dr #D10",
  "18038": "Waterfront City/Docklands Dr #D11",
  "18039": "NewQuay Prom/Docklands Dr #D10",
  "18040": "Docklands Stadium/La Trobe St  #D1",
  "18045": "Melbourne Central Station/La Trobe St  #5",
  "18046": "Melbourne Central & State Library stations/La Trobe St (Melb... #6",
  "18049": "Victoria St/La Trobe St #9",
  "18050": "Nicholson St/Victoria Pde #10",
  "18051": "St Vincents Plaza/Victoria Pde #12",
  "18052": "Central Pier/Harbour Esp #D2",
  "18053": "Stadium Precinct - Bourke St/Harbour Esp #D3",
  "18054": "Docklands Park/Harbour Esp #D4",
  "18055": "South Wharf/Wurundjeri Way #D5",
  "18056": "Flinders Street West/Flinders St #D6",
  "18059": "Haines St/Abbotsford St #16",
  "18060": "Arden St/Abbotsford St #15",
  "18061": "Queensberry St/Abbotsford St #14",
  "18064": "Elliott Ave/Royal Park #24",
  "18065": "State Netball Hockey Centre/Royal Park #25",
  "18066": "Melbourne Zoo/Royal Park #26",
  "18067": "Royal Park Station/Royal Park #27",
  "18068": "Park St/Royal Park #28",
  "18069": "Brunswick Rd/Grantham St #29",
  "18071": "Union Square Shopping Centre/Grantham St #30",
  "18072": "Grantham St/Dawson St #31",
  "18075": "Smith St/Melville Rd #34",
  "18076": "Victoria St/Melville Rd #35",
  "18077": "Hope St/Melville Rd #36",
  "18078": "Albion St/Melville Rd #37",
  "18079": "Jacobs Reserve/Melville Rd #38",
  "18081": "Moreland Rd/Melville Rd #40",
  "18083": "Reynard St/Melville Rd #42",
  "18084": "Princes Tce/Melville Rd #43",
  "18085": "Brearley Pde/Melville Rd #44",
  "18086": "Bell St/Melville Rd #45",
  "18087": "Market St/Flinders St #3",
  "18089": "Elizabeth St/Flinders St #4",
  "18090": "Swanston St/Flinders St #5",
  "18091": "Russell St/Flinders St #6",
  "18092": "Spring St/Flinders St #8",
  "18093": "Lansdowne St/Wellington Pde #9",
  "18094": "Jolimont Rd/Wellington Pde #10",
  "18095": "Jolimont Station-MCG/Wellington Pde #11",
  "18097": "Simpson St/Wellington Pde #13",
  "18098": "Punt Rd/Wellington Pde #14",
  "18099": "Punt Rd/Bridge Rd #14",
  "18100": "Simpson St/Wellington Pde #13",
  "18102": "Jolimont Station-MCG/Wellington Pde #11",
  "18103": "Jolimont Rd/Wellington Pde #10",
  "18104": "Lansdowne St/Wellington Pde #9",
  "18105": "Spring St/Flinders St #8",
  "18108": "Rod Laver Arena/MCG Gates 1-3 #7B",
  "18116": "MCG Gates 4-7/John Cain Arena #7C",
  "18118": "Olympic Boulevard #7D",
  "18155": "Olympic Boulevard #7D",
  "18161": "MCG Gates 4-7/John Cain Arena #7C",
  "18172": "Rod Laver Arena/MCG Gates 1-3 #7B",
  "18174": "Russell St/Flinders St #6",
  "18175": "Swanston St/Flinders St #5",
  "18176": "Elizabeth St/Flinders St #4",
  "18178": "Market St/Flinders St #3",
  "18179": "Victoria Police Centre/Flinders St #D6",
  "18180": "South Wharf/Wurundjeri Way #D5",
  "18181": "Docklands Park/Harbour Esp #D4",
  "18182": "Stadium Precinct - Bourke St/Harbour Esp #D3",
  "18183": "Central Pier/Harbour Esp #D2",
  "18184": "Clarendon St/Whiteman St #125",
  "18185": "Casino/MCEC/Clarendon St #124A",
  "18186": "Batman Park/Spencer St #124",
  "18187": "Southern Cross Railway Station/Spencer St #122",
  "18189": "Lonsdale St/Spencer St #120",
  "18190": "La Trobe St/Spencer St #119",
  "18192": "Lonsdale St/Spencer St #120",
  "18194": "Southern Cross Railway Station/Spencer St #122",
  "18196": "Batman Park/Spencer St #124",
  "18197": "Casino/MCEC/Clarendon St #124A",
  "18199": "Bourke St/William St #5",
  "18201": "Flagstaff Railway Station/William St #7",
  "18203": "Victoria St/Peel St #10",
  "18204": "Victoria St/Peel St #10",
  "18205": "Queen Victoria Market/Peel St #9",
  "18206": "Queen Victoria Market/Peel St #9",
  "18208": "Flagstaff Railway Station/William St #7",
  "18210": "Bourke St/William St #5",
  "18211": "Collins St/William St #4",
  "18214": "Flinders St/Queens Bridge St #1",
  "18215": "Casino/Southbank/Queens Bridge St #115",
  "18217": "York St/Kings Way #117",
  "18219": "Wells St/Park St #119",
  "18221": "Wells St/Park St #119",
  "18222": "Sturt St/Kings Way #118",
  "18224": "Kings Way/Sturt St #20",
  "18225": "Miles St/Sturt St #19",
  "18226": "Grant St/Sturt St #18",
  "18227": "Arts Precinct/Sturt St #17",
  "18229": "Arts Precinct/Sturt St #17",
  "18230": "Grant St/Sturt St #18",
  "18231": "Miles St/Sturt St #19",
  "18232": "Kings Way/Sturt St #20",
  "18233": "City Rd/Kings Way #116",
  "18341": "Grattan St/Church St #24",
  "18342": "Brook St/Church St #25",
  "18343": "Barkers Rd/Church St #26",
  "18347": "Pakington St/High St #34",
  "18348": "Cobden St/High St #35",
  "18349": "Parkhill Rd/High St #36",
  "18350": "Kew Cemetery/High St #37",
  "18351": "Victoria Park/High St #38",
  "18352": "Harp Rd/High St #39",
  "18353": "Harp Village/High St #40",
  "18354": "Clyde St/High St #41",
  "18355": "Irymple Ave/High St #42",
  "18356": "Kew High School/High St #43",
  "18357": "Burke Rd/High St #44",
  "18359": "Wattle Ave/Doncaster Rd #46",
  "18360": "North Balwyn Shopping Centre/Doncaster Rd #47",
  "18361": "Sunburst Ave/Doncaster Rd #48",
  "18362": "Cityview Rd/Doncaster Rd #49",
  "18363": "Hill Rd/Doncaster Rd #50",
  "18364": "St Kilda Primary School/Brighton Rd #36",
  "18365": "Wimbledon Ave/Brighton Rd #38",
  "18367": "Glen Eira Rd/Brighton Rd #39",
  "18368": "Scott St/Brighton Rd #40",
  "18369": "Coleridge St/Brighton Rd #41",
  "18370": "Hotham St/Brighton Rd #42",
  "18371": "Brighton Rd/Glenhuntly Rd #43",
  "18372": "Elsternwick Railway Station/Glenhuntly Rd #44",
  "18373": "Elsternwick Shopping Centre/Glenhuntly Rd #45",
  "18374": "Orrong Rd/Glenhuntly Rd #46",
  "18375": "Shoobra Rd/Glenhuntly Rd #47",
  "18376": "Parkside St/Glenhuntly Rd #48",
  "18392": "Kooyong Rd/Glenhuntly Rd #49",
  "18393": "Royal Pde/Glenhuntly Rd #50",
  "18394": "Hawthorn Rd/Glenhuntly Rd #51",
  "18395": "Jasmine St/Glenhuntly Rd #52",
  "18396": "Glenhuntly Tram Depot/Glenhuntly Rd #53",
  "18397": "Bambra Rd/Glenhuntly Rd #54",
  "18398": "Fallon St/Glenhuntly Rd #55",
  "18399": "Kean St/Glenhuntly Rd #56",
  "18400": "Laura St/Glenhuntly Rd #57",
  "18401": "Booran Rd/Glenhuntly Rd #58",
  "18403": "Glenhuntly Shops/Glenhuntly Rd #60",
  "18404": "Glen Huntly Railway Station/Glen Huntly Rd  #61",
  "18405": "Grange Rd/Glenhuntly Rd #62",
  "18406": "Maroona Rd/Glenhuntly Rd #63",
  "18407": "Mernda Ave/Glenhuntly Rd #64",
  "18408": "Mimosa Rd/Glenhuntly Rd #65",
  "18409": "Glenhuntly Rd/Truganini Rd #66",
  "18410": "Centre Rd/Truganini Rd #67",
  "18411": "Carnegie/Truganini Rd #68",
  "18412": "East Brighton/Hawthorn Rd #68",
  "18413": "Howell St/Hawthorn Rd #67",
  "18414": "Union St/Hawthorn Rd #66",
  "18415": "Davey Ave/Hawthorn Rd #65",
  "18416": "Taylor St/Hawthorn Rd #64",
  "18417": "North Rd/Hawthorn Rd #63",
  "18418": "Gardenvale Rd/Hawthorn Rd #62",
  "18419": "Raynes St/Hawthorn Rd #61",
  "18420": "Dover St/Hawthorn Rd #60",
  "18421": "Princes Park/Hawthorn Rd #59",
  "18422": "Sycamore St/Hawthorn Rd #58",
  "18423": "Glenhuntly Rd/Hawthorn Rd #57",
  "18424": "Lockhart St/Hawthorn Rd #56",
  "18425": "Sylverly Gr/Hawthorn Rd #55",
  "18426": "Glen Eira Rd/Hawthorn Rd #54",
  "18427": "Crotonhurst Ave/Hawthorn Rd #53",
  "18428": "Halstead St/Hawthorn Rd #52",
  "18429": "Balaclava Rd/Hawthorn Rd #51",
  "18430": "Inkerman Rd/Hawthorn Rd #50",
  "18431": "Wanda Rd/Hawthorn Rd #49",
  "18432": "Dandenong Rd/Hawthorn Rd #48A",
  "18437": "Bailey Ave/Dandenong Rd #44",
  "18438": "Matlock Ct/Dandenong Rd #43",
  "18439": "Kooyong Rd/Dandenong Rd #42",
  "18441": "Wattletree Rd/Dandenong Rd #40",
  "18443": "Orrong Rd/Dandenong Rd #38",
  "18444": "Lansdowne Rd/Dandenong Rd #37",
  "18445": "Alexandra St/Dandenong Rd #36",
  "18446": "Williams Rd/Dandenong Rd #35",
  "18447": "Westbury St/Dandenong Rd #34",
  "18448": "Hornby St/Dandenong Rd #33",
  "18449": "Chapel St/Dandenong Rd #32",
  "18450": "Casino/Southbank/Queens Bridge St #115",
  "18451": "Darling Rd/Waverley Rd #64",
  "18452": "Hughes St/Waverley Rd #63",
  "18453": "Macgregor St/Waverley Rd #62",
  "18454": "Tennyson St/Waverley Rd #61",
  "18455": "Burke Rd/Waverley Rd #60",
  "18456": "Dandenong Rd/Waverley Rd #59",
  "18457": "Caulfield Railway Station/Derby Rd #57",
  "18459": "Caulfield Racecourse/Normanby Rd #56",
  "18460": "Balaclava Rd/Normanby Rd #55",
  "18461": "Kambrook Rd/Balaclava Rd #54",
  "18462": "Caulfield Park/Balaclava Rd #53",
  "18463": "Caulfield Park Bowling Club/Balaclava Rd #52",
  "18464": "Hawthorn Rd/Balaclava Rd #51",
  "18465": "Flinders St/Queens Bridge St #1",
  "18468": "Caulfield Junior College/Balaclava Rd #47",
  "18469": "Collins St/William St #4",
  "18479": "Wharton St/Whitehorse Rd #50",
  "18481": "Dorcas St/Eastern Rd #22",
  "18482": "Moray St/Park St #23",
  "18483": "Clarendon St/Park St #24",
  "18484": "Cecil St/Park St #25",
  "18485": "Maribyrnong Park/Maribyrnong Rd #41",
  "18486": "Clyde St/Raleigh Rd #42",
  "18487": "Van Ness Ave/Raleigh Rd #43",
  "18488": "Warrs Rd/Raleigh Rd #44",
  "18489": "Maribyrnong Community Centre/Raleigh Rd #45",
  "18490": "Rosamond Rd/Raleigh Rd #46",
  "18491": "Wests Rd/Raleigh Rd #48",
  "18492": "Highpoint Shopping Centre/Wests Rd #49",
  "18493": "Williamson Rd/Wests Rd #50",
  "18494": "Williamson Rd/Rosamond Rd #51",
  "18495": "River St/Rosamond Rd #52",
  "18496": "Maribyrnong College/River St #53",
  "18497": "Gordon St/River St #54",
  "18498": "Lyric St/Gordon St #55",
  "18499": "Edgewater Square/Gordon St #56",
  "18500": "Titch St/Gordon St #57",
  "18501": "Ballarat Rd/Gordon St #58",
  "18505": "Droop St/Ballarat Rd #59",
  "18506": "Tiernan St/Droop St #60",
  "18507": "Geelong Rd/Droop St #61",
  "18508": "Nicholson St/Droop St #62",
  "18509": "Leeds St/Hopkins St #63",
  "18511": "Chaucer St/Ascot Vale Rd #33",
  "18512": "Maribyrnong Rd/Ascot Vale Rd #34",
  "18513": "Moore St/Maribyrnong Rd #35",
  "18515": "Union Rd/Maribyrnong Rd #37",
  "18516": "Ferguson St/Maribyrnong Rd #38",
  "18517": "Bowen St/Maribyrnong Rd #39",
  "18518": "Epsom Rd/Maribyrnong Rd #40",
  "18519": "Maribyrnong Rd/Union Rd #37",
  "18520": "St Leonards Rd/Union Rd #36",
  "18521": "Munro St/Union Rd #35",
  "18522": "Burrowes St/Union Rd #34",
  "18524": "Sandown Rd/Epsom Rd #32",
  "18525": "Racing Victoria/Epsom Rd #31",
  "18526": "Flemington Racecourse/Epsom Rd #30",
  "18527": "Flemington Racecourse/Racecourse Rd #29",
  "18528": "Smithfield Rd/Racecourse Rd #28",
  "18529": "Newmarket Plaza/Racecourse Rd #26",
  "18530": "Wellington St/Racecourse Rd #25",
  "18531": "Collett St/Racecourse Rd #24",
  "18532": "Stubbs St/Racecourse Rd #23",
  "18533": "Boundary Rd/Racecourse Rd #22",
  "18536": "Abbotsford St Interchange/Abbotsford St #19",
  "18539": "Haines St/Abbotsford St #16",
  "18540": "Arden St/Abbotsford St #15",
  "18541": "Abbotsford St/Queensberry St #14",
  "18544": "Elliott Ave/Royal Park #24",
  "18545": "State Netball Hockey Centre/Royal Park #25",
  "18546": "Melbourne Zoo/Royal Park #26",
  "18547": "Royal Park Station/Royal Park #27",
  "18548": "Park St/Royal Park #28",
  "18550": "Union Square Shopping Centre/Grantham St #30",
  "18551": "Dawson St/Grantham St #31",
  "18553": "Daly St/Dawson St #33",
  "18554": "Smith St/Melville Rd #34",
  "18555": "Victoria St/Melville Rd #35",
  "18556": "Hope St/Melville Rd #36",
  "18557": "Albion St/Melville Rd #37",
  "18560": "Moreland Rd/Melville Rd #40",
  "18563": "Princes Tce/Melville Rd #43",
  "18564": "Brearley Pde/Melville Rd #44",
  "18566": "Balwyn Rd/Doncaster Rd #51",
  "18567": "Dight Ave/Doncaster Rd #50",
  "18568": "Buchanan Ave/Doncaster Rd #49",
  "18569": "Osburn Ave/Doncaster Rd #48",
  "18570": "North Balwyn Shopping Centre/Doncaster Rd #47",
  "18571": "Wattle Ave/Doncaster Rd #46",
  "18573": "Ferrars St/Park St #26",
  "18574": "Kew High School/High St #43",
  "18575": "Woodlands Ave/High St #42",
  "18576": "Station St/High St #41",
  "18577": "Harp Village/High St #40",
  "18578": "Harp Rd/High St #39",
  "18579": "Victoria Park/High St #38",
  "18580": "Kew Cemetery/High St #37",
  "18581": "Gladstone St/High St #36",
  "18582": "Charles St/High St #35",
  "18583": "Union St/High St #34",
  "18584": "Kew Shopping Centre/High St #33",
  "18588": "Brook St/Church St #25",
  "18589": "Hill St/Church St #24",
  "18591": "Victoria St/Church St #65",
  "18592": "Elizabeth St/Church St #64",
  "18593": "Tweedie Pl/Church St #63",
  "18594": "Highett St/Church St #62",
  "18595": "Bridge Rd/Church St #61",
  "18596": "Abinger St/Church St #60",
  "18597": "St Ignatius Church/Church St #59",
  "18598": "Gipps St/Church St #58",
  "18599": "Swan St/Church St #57",
  "18601": "Adelaide St/Church St #55",
  "18602": "Cotter St/Church St #54",
  "18603": "Howard St/Church St #53",
  "18605": "Malcolm St/Chapel St #51",
  "18606": "Toorak Rd/Chapel St #50",
  "18607": "Arthur St/Chapel St #49",
  "18608": "Cliff St/Chapel St #48",
  "18609": "Commercial Rd/Chapel St #47",
  "18610": "Chatham St/Chapel St #46",
  "18611": "High St/Chapel St #45",
  "18612": "Duke St/Chapel St #44",
  "18613": "Windsor Railway Station/Chapel St #43",
  "18614": "Dandenong Rd/Chapel St #42",
  "18615": "St Michaels Grammar School/Chapel St #41",
  "18616": "Alma Rd/Chapel St #40",
  "18617": "Argyle St/Chapel St #39",
  "18618": "Inkerman St/Chapel St #38",
  "18619": "Chapel St/Carlisle St #37",
  "18620": "St Kilda Town Hall/Carlisle St #36",
  "18621": "Carlisle St/Chapel St #37",
  "18622": "Brighton Rd/Chapel St #36",
  "18623": "St Kilda Rd/Carlisle St #35",
  "18624": "Greeves St/Carlisle St #34",
  "18625": "Barkly St/Carlisle St #33",
  "18632": "Balaclava Station/Carlisle St #38",
  "18633": "Orange Gr/Carlisle St #39",
  "18634": "Hotham St/Carlisle St #40",
  "18635": "Empress Rd/Balaclava Rd #41",
  "18636": "Sidwell Ave/Balaclava Rd #42",
  "18637": "Orrong Rd/Balaclava Rd #43",
  "18638": "Ontario St/Balaclava Rd #44",
  "18639": "Kent Gr/Balaclava Rd #45",
  "18640": "Kooyong Rd/Balaclava Rd #46",
  "18641": "Elmhurst Rd/Balaclava Rd #47",
  "18645": "Hawthorn Rd/Balaclava Rd #51",
  "18646": "Caulfield Park Bowling Club/Balaclava Rd #52",
  "18647": "Caulfield Park/Balaclava Rd #53",
  "18648": "Kambrook Rd/Balaclava Rd #54",
  "18649": "Normanby Rd/Balaclava Rd #55",
  "18650": "Caulfield Racecourse/Normanby Rd #56",
  "18651": "Caulfield Railway Station/Derby Rd #57",
  "18652": "Dandenong Rd/Derby Rd #58",
  "18653": "Dandenong Rd/Waverley Rd #59",
  "18654": "Burke Rd/Waverley Rd #60",
  "18655": "Tennyson St/Waverley Rd #61",
  "18656": "The Avenue/Waverley Rd #62",
  "18657": "Oak Gr/Waverley Rd #63",
  "18658": "Park St/Montague St #27",
  "18659": "Montague St/Bridport St #28",
  "18660": "Bridport St/Victoria Ave #29",
  "18661": "Richardson St/Victoria Ave #30",
  "18662": "Graham St/Victoria Ave #31",
  "18663": "Beaconsfield Pde/Victoria Ave #32",
  "18699": "Walsh St/Toorak Rd #124",
  "18700": "Punt Rd/Toorak Rd #125",
  "18703": "South Yarra Railway Station/Toorak Rd #127",
  "18704": "Chapel St/Toorak Rd #128",
  "18705": "Tivoli Rd/Toorak Rd #129",
  "18706": "Hawksburn Rd/Toorak Rd #130",
  "18707": "Williams Rd/Toorak Rd #131",
  "18708": "Toorak Village/Toorak Rd #132",
  "18709": "Canterbury Rd/Toorak Rd #133",
  "18710": "Deepdene Shopping Centre/Whitehorse Rd #43",
  "18712": "Brunswick Rd/Lygon St #120",
  "18713": "Weston St/Lygon St #121",
  "18714": "Glenlyon Rd/Lygon St #122",
  "18715": "Albert St/Lygon St #123",
  "18716": "Victoria St/Lygon St #124",
  "18717": "Blyth St/Lygon St #125",
  "18718": "Stewart St/Lygon St #126",
  "18719": "Albion St/Lygon St #127",
  "18720": "Mitchell St/Holmes St #128",
  "18721": "Moreland Rd/Holmes St #129",
  "18722": "Barrow St/Moreland Rd #130",
  "18723": "De Carle St/Moreland Rd #131",
  "18724": "Sydney Rd/Moreland Rd #132",
  "18725": "Moreland Station/Moreland Rd #133",
  "18726": "The Avenue/Nicholson St #130",
  "18727": "Rennie St/Nicholson St #131",
  "18728": "Crozier St/Nicholson St #132",
  "18729": "Harding St/Nicholson St #133",
  "18730": "Merribell Ave/Nicholson St #134",
  "18732": "Deepdene Park/Whitehorse Rd #44",
  "18733": "Hardwicke St/Whitehorse Rd #45",
  "18734": "Balwyn Cinema/Whitehorse Rd #46",
  "18735": "Balwyn Rd/Whitehorse Rd #47",
  "18736": "Balwyn Shopping Centre/Whitehorse Rd #48",
  "18737": "Northcote Ave/Whitehorse Rd #49",
  "18738": "Narrak Rd/Whitehorse Rd #51",
  "18781": "Orrong Rd/Toorak Rd #134",
  "18782": "Woorigoleen Rd/Toorak Rd #135",
  "18783": "Irving Rd/Toorak Rd #136",
  "18784": "Kooyong Rd/Toorak Rd #137",
  "18785": "Moonga Rd/Toorak Rd #138",
  "18786": "Glenbervie Rd/Toorak Rd #139",
  "18789": "Lygon St/Elgin St #112",
  "18790": "Lytton St/Lygon St #113",
  "18791": "Princes St/Lygon St #114",
  "18792": "Melbourne Cemetery/Lygon St #115",
  "18793": "Fenwick St/Lygon St #116",
  "18794": "Richardson St/Lygon St #117",
  "18795": "Pigdon St/Lygon St #118",
  "18899": "Alfred Hospital/Commercial Rd #26",
  "18918": "Punt Rd/Commercial Rd #27",
  "18923": "Braille Library/Commercial Rd #28",
  "18931": "Porter St/Commercial Rd #29",
  "18933": "Prahran Market/Commercial Rd #30",
  "18934": "Chapel St/Commercial Rd #31",
  "18935": "Surrey Rd/Malvern Rd #32",
  "18936": "Francis St/Malvern Rd #33",
  "18937": "Williams Rd/Malvern Rd #34",
  "18938": "Mathoura Rd/Malvern Rd #35",
  "18939": "A'Beckett St/Malvern Rd #36",
  "18940": "Orrong Rd/Malvern Rd #37",
  "18941": "Clendon Rd/Malvern Rd #38",
  "18942": "Irving Rd/Malvern Rd #39",
  "18943": "Kooyong Rd/Malvern Rd #40",
  "18944": "Albany Rd/Malvern Rd #41",
  "18945": "Lauriston Girls School/Malvern Rd #42",
  "18946": "Glenferrie Rd/Malvern Rd #43",
  "18947": "Plant St/Malvern Rd #44",
  "18948": "Elizabeth St/Malvern Rd #45",
  "18949": "Meredith St/Malvern Rd #46",
  "18950": "Tooronga Rd/Malvern Rd #47",
  "18951": "Edgar St/Malvern Rd #48",
  "18952": "Kenilworth Gr/Malvern Rd #49",
  "18953": "Burke Rd/Malvern Rd #50",
  "18954": "Gardiner Railway Station/Burke Rd #51",
  "18955": "Harris Ave/Burke Rd #52",
  "18957": "Toorak Rd/Burke Rd #54",
  "18958": "Middle Rd/Burke Rd #55",
  "18959": "Anderson Rd/Burke Rd #56",
  "18960": "Pine Ave/Burke Rd #57",
  "18961": "Leura Gr/Burke Rd #58",
  "18962": "Pleasant Rd/Burke Rd #59",
  "18964": "Riversdale Rd/Burke Rd #61",
  "18965": "Camberwell Shopping Centre/Burke Rd #62",
  "18966": "Prospect Hill Rd/Burke Rd #63",
  "18967": "Camberwell Station/Burke Rd #64",
  "18968": "Victoria Rd/Burke Rd #65",
  "18969": "Rathmines Rd/Burke Rd #66",
  "18970": "Camberwell Girls Grammar/Burke Rd #67",
  "18971": "Mont Albert Rd/Burke Rd #68",
  "18972": "Sackville St/Burke Rd #69",
  "18973": "St Kilda Primary School/Brighton Rd #36",
  "18974": "Chapel St/Brighton Rd #37",
  "18975": "Brunning St/Brighton Rd #38",
  "18976": "Glen Eira Rd/Brighton Rd #39",
  "18977": "Scott St/Brighton Rd #40",
  "18978": "Coleridge St/Brighton Rd #41",
  "18979": "Hotham St/Brighton Rd #42",
  "18980": "Brighton Rd/Glenhuntly Rd #43",
  "18981": "Elsternwick Railway Station/Glenhuntly Rd #44",
  "18982": "Elsternwick Shopping Centre/Glenhuntly Rd #45",
  "18983": "Orrong Rd/Glenhuntly Rd #46",
  "18984": "Shoobra Rd/Glenhuntly Rd #47",
  "18985": "Parkside St/Glenhuntly Rd #48",
  "18986": "Kooyong Rd/Glenhuntly Rd #49",
  "18987": "Royal Pde/Glenhuntly Rd #50",
  "19000": "Rogers Ave/Hawthorn Rd #67",
  "19001": "Union St/Hawthorn Rd #66",
  "19002": "Davey Ave/Hawthorn Rd #65",
  "19003": "Taylor St/Hawthorn Rd #64",
  "19004": "North Rd/Hawthorn Rd #63",
  "19005": "Gardenvale Rd/Hawthorn Rd #62",
  "19006": "Stone St/Hawthorn Rd #61",
  "19007": "Dover St/Hawthorn Rd #60",
  "19008": "Princes Park/Hawthorn Rd #59",
  "19009": "Sycamore St/Hawthorn Rd #58",
  "19010": "Glenhuntly Rd/Hawthorn Rd #57",
  "19011": "Briggs St/Hawthorn Rd #56",
  "19012": "Sylverly Gr/Hawthorn Rd #55",
  "19013": "Glen Eira Rd/Hawthorn Rd #54",
  "19014": "Northcote Ave/Hawthorn Rd #53",
  "19015": "Halstead St/Hawthorn Rd #52",
  "19016": "Balaclava Rd/Hawthorn Rd #51",
  "19017": "Inkerman Rd/Hawthorn Rd #50",
  "19018": "Arthur St/Hawthorn Rd #49",
  "19019": "Hawthorn Rd/Dandenong Rd #48",
  "19023": "Bailey Ave/Dandenong Rd #44",
  "19024": "Egerton Rd/Dandenong Rd #43",
  "19025": "Kooyong Rd/Dandenong Rd #42",
  "19027": "Wattletree Rd/Dandenong Rd #40",
  "19028": "Orrong Rd/Dandenong Rd #38",
  "19029": "Lansdowne Rd/Dandenong Rd #37",
  "19030": "Closeburn Ave/Dandenong Rd #36",
  "19031": "Williams Rd/Dandenong Rd #35",
  "19032": "The Avenue/Dandenong Rd #34",
  "19033": "Hornby St/Dandenong Rd #33",
  "19034": "Chapel St/Dandenong Rd #32",
  "19035": "Queens Way/Queens Way #31",
  "19036": "Cotham Rd/Burke Rd #70",
  "19037": "Peverill St/Burke Rd #69",
  "19038": "Mont Albert Rd/Burke Rd #68",
  "19039": "Camberwell Girls Grammar/Burke Rd #67",
  "19040": "Canterbury Rd/Burke Rd #66",
  "19041": "Victoria Rd/Burke Rd #65",
  "19042": "Camberwell Station/Burke Rd #64",
  "19043": "Prospect Hill Rd/Burke Rd #63",
  "19044": "Camberwell Junction/Burke Rd #61",
  "19046": "Seymour Gr/Burke Rd #59",
  "19047": "Currajong Ave/Burke Rd #58",
  "19048": "Pine Ave/Burke Rd #57",
  "19049": "Anderson Rd/Burke Rd #56",
  "19050": "Middle Rd/Burke Rd #55",
  "19051": "Toorak Rd/Burke Rd #54",
  "19053": "Bickleigh St/Burke Rd #52",
  "19054": "Gardiner Station/Burke Rd #51",
  "19056": "Glenarm Rd/Malvern Rd #50",
  "19057": "Belmont Ave/Malvern Rd #49",
  "19058": "Edgar St/Malvern Rd #48",
  "19059": "Tooronga Rd/Malvern Rd #47",
  "19060": "Shaftesbury Ave/Malvern Rd #46",
  "19061": "Elizabeth St/Malvern Rd #45",
  "19062": "Plant St/Malvern Rd #44",
  "19063": "Glenferrie Rd/Malvern Rd #43",
  "19064": "Lauriston Girls School/Malvern Rd #42",
  "19065": "Murray St/Malvern Rd #41",
  "19066": "Kooyong Rd/Malvern Rd #40",
  "19067": "Densham Rd/Malvern Rd #39",
  "19068": "Clendon Rd/Malvern Rd #38",
  "19069": "Orrong Rd/Malvern Rd #37",
  "19070": "Hawthorn Rd/Glenhuntly Rd #51",
  "19071": "Jasmine St/Glenhuntly Rd #52",
  "19072": "Glenhuntly Tram Depot/Glenhuntly Rd #53",
  "19073": "Bambra Rd/Glenhuntly Rd #54",
  "19074": "Fallon St/Glenhuntly Rd #55",
  "19075": "Kambrook Rd/Glenhuntly Rd #56",
  "19076": "Clarke Ave/Glenhuntly Rd #57",
  "19077": "Booran Rd/Glenhuntly Rd #58",
  "19078": "Glenhuntly Shops/Glenhuntly Rd #60",
  "19079": "Glen Huntly Railway Station/Glen Huntly Rd  #61",
  "19081": "Grange Rd/Glenhuntly Rd #62",
  "19082": "Maroona Rd/Glenhuntly Rd #63",
  "19083": "Mernda Ave/Glenhuntly Rd #64",
  "19084": "Mimosa Rd/Glenhuntly Rd #65",
  "19085": "Truganini Rd/Glenhuntly Rd #66",
  "19086": "Centre Rd/Truganini Rd #67",
  "19087": "Baker St/Church St #64",
  "19088": "Kent St/Church St #63",
  "19089": "Highett St/Church St #62",
  "19090": "Bridge Rd/Church St #61",
  "19091": "Abinger St/Church St #60",
  "19092": "St Ignatius Church/Church St #59",
  "19093": "Gipps St/Church St #58",
  "19094": "Swan St/Church St #57",
  "19095": "East Richmond Railway Station/Church St #56",
  "19096": "Gibbons St/Church St #55",
  "19097": "Balmain St/Church St #54",
  "19098": "Howard St/Church St #53",
  "19100": "Malcolm St/Chapel St #51",
  "19101": "Toorak Rd/Chapel St #50",
  "19102": "Palermo St/Chapel St #49",
  "19103": "Wilson St/Chapel St #48",
  "19104": "Malvern Rd/Chapel St #47",
  "19105": "Chatham St/Chapel St #46",
  "19106": "High St/Chapel St #45",
  "19107": "Duke St/Chapel St #44",
  "19108": "Windsor Railway Station/Chapel St #43",
  "19109": "Dandenong Rd/Chapel St #42",
  "19110": "St Michaels Grammar School/Chapel St #41",
  "19111": "Alma Rd/Chapel St #40",
  "19112": "Argyle St/Chapel St #39",
  "19113": "Inkerman St/Chapel St #38",
  "19115": "St Kilda Town Hall/Carlisle St #36",
  "19116": "Carlisle St/Chapel St #37",
  "19118": "Brighton Rd/Carlisle St #35",
  "19119": "Mitchell St/Carlisle St #34",
  "19123": "Canterbury Rd/Malvern Rd #36",
  "19124": "Lorne Rd/Malvern Rd #35",
  "19125": "Williams Rd/Malvern Rd #34",
  "19126": "Hobson St/Malvern Rd #33",
  "19127": "Bendigo St/Malvern Rd #32",
  "19128": "Chapel St/Malvern Rd #31",
  "19129": "Prahran Market/Commercial Rd #30",
  "19130": "Porter St/Commercial Rd #29",
  "19131": "Braille Library/Commercial Rd #28",
  "19132": "Punt Rd/Commercial Rd #27",
  "19133": "Alfred Hospital/Commercial Rd #26",
  "19135": "Barkly St/Carlisle St #33",
  "19136": "Havelock St/Carlisle St #32",
  "19250": "Curzon St/Queensberry St #13",
  "19251": "North Melbourne Town Hall/Queensberry St #12",
  "19253": "Royal Melbourne Hospital/Flemington Rd #14",
  "19256": "Royal Childrens Hospital/Flemington Rd #19",
  "19259": "Flemington Bridge Station/Flemington Rd #22",
  "19260": "Djerring Flemington Hub/Mt Alexander Rd  #23",
  "19261": "Mooltan St/Mt Alexander Rd #24",
  "19262": "Mount Alexander College/Mt Alexander Rd #25",
  "19263": "Wellington St/Mt Alexander Rd #26",
  "19264": "Essendon Tram Depot/Mt Alexander Rd #27",
  "19265": "Middle St/Mt Alexander Rd #28",
  "19266": "Warrick St/Mt Alexander Rd #29",
  "19267": "Ormond Rd/Mt Alexander Rd #30",
  "19268": "Montgomery St/Mt Alexander Rd #31",
  "19269": "Moonee Ponds Junction/Pascoe Vale Rd #32",
  "19270": "Moonee Valley Civic Centre/Pascoe Vale Rd #34",
  "19271": "Queens Park/Pascoe Vale Rd #35",
  "19272": "Salisbury St/Pascoe Vale Rd #36",
  "19274": "Pascoe Vale Rd/Fletcher St #38",
  "19275": "Hoddle St/Fletcher St #39",
  "19276": "Nicholson St/Fletcher St #40",
  "19277": "Fletcher St/Napier St #41",
  "19278": "Richmond Station/Swan St #8",
  "19279": "Lennox St/Swan St #9",
  "19280": "Swan Street Shopping Centre/Swan St #10",
  "19281": "Church St/Swan St #11",
  "19282": "Coppin St/Swan St #12",
  "19283": "Edinburgh St/Swan St #13",
  "19294": "Burnley St/Swan St #14",
  "19295": "Stawell St/Swan St #15",
  "19296": "Park Gr/Swan St #16",
  "19297": "Madden Gr/Swan St #17",
  "19298": "Yarra Bvd/Swan St #18",
  "19299": "Power St/Riversdale Rd #29",
  "19300": "Through St/Riversdale Rd #30",
  "19301": "Fordholm Rd/Riversdale Rd #31",
  "19302": "Glenferrie Rd/Riversdale Rd #32",
  "19303": "Berkeley St/Riversdale Rd #33",
  "19304": "Port Junction/Whiteman St #125",
  "19305": "Dorcas St/Eastern Rd #22",
  "19306": "Moray St/Park St #23",
  "19307": "Clarendon St/Park St #24",
  "19308": "Cecil St/Park St #25",
  "19309": "Ferrars St/Park St #26",
  "19310": "Montague St/Park St #27",
  "19311": "Bridport St/Montague St #28",
  "19312": "Bridport St/Victoria Ave #29",
  "19313": "Richardson St/Victoria Ave #30",
  "19314": "Graham St/Victoria Ave #31",
  "19322": "Walsh St/Toorak Rd #124",
  "19323": "Punt Rd/Toorak Rd #125",
  "19325": "South Yarra Railway Station/Toorak Rd #127",
  "19326": "Chapel St/Toorak Rd #128",
  "19327": "Tivoli Rd/Toorak Rd #129",
  "19328": "Hawksburn Rd/Toorak Rd #130",
  "19329": "Williams Rd/Toorak Rd #131",
  "19330": "Toorak Village/Toorak Rd #132",
  "19331": "Grange Rd/Toorak Rd #133",
  "19332": "Orrong Rd/Toorak Rd #134",
  "19333": "Woorigoleen Rd/Toorak Rd #135",
  "19334": "Irving Rd/Toorak Rd #136",
  "19335": "Kooyong Rd/Toorak Rd #137",
  "19336": "Moonga Rd/Toorak Rd #138",
  "19338": "Glenferrie Rd/Toorak Rd #139",
  "19340": "Lygon St/Elgin St #112",
  "19341": "Lytton St/Lygon St #113",
  "19342": "Princes St/Lygon St #114",
  "19343": "Melbourne Cemetery/Lygon St #115",
  "19344": "Fenwick St/Lygon St #116",
  "19345": "Richardson St/Lygon St #117",
  "19346": "Pigdon St/Lygon St #118",
  "19348": "Brunswick Rd/Lygon St #120",
  "19349": "Weston St/Lygon St #121",
  "19350": "Glenlyon Rd/Lygon St #122",
  "19351": "Albert St/Lygon St #123",
  "19352": "Victoria St/Lygon St #124",
  "19353": "Blyth St/Lygon St #125",
  "19354": "Stewart St/Lygon St #126",
  "19355": "Albion St/Holmes St #127",
  "19356": "Mitchell St/Holmes St #128",
  "19357": "Moreland Rd/Nicholson St #129",
  "19358": "Moreland Rd/Holmes St #129",
  "19359": "Barrow St/Moreland Rd #130",
  "19360": "De Carle St/Moreland Rd #131",
  "19361": "Sydney Rd/Moreland Rd #132",
  "19362": "Moreland Station/Cameron St #133",
  "19363": "The Avenue/Nicholson St #130",
  "19364": "Rennie St/Nicholson St #131",
  "19365": "Crozier St/Nicholson St #132",
  "19366": "Harding St/Nicholson St #133",
  "19367": "Merribell Ave/Nicholson St #134",
  "19368": "Bell St/Nicholson St #135",
  "19369": "Southbank Tram Depot/Light Rail #125A",
  "19370": "Montague St/Light Rail #126",
  "19371": "North Port Station/Light Rail #127",
  "19372": "Graham St/Light Rail #128",
  "19374": "Lansdowne St/Victoria Pde #13",
  "19376": "Grice Cres/Mt Alexander Rd #42",
  "19377": "Wellington St/Victoria Pde #16",
  "19379": "Hoddle St/Victoria Pde #18",
  "19381": "North Richmond Railway Station/Victoria St #19",
  "19382": "Lennox St/Victoria St #20",
  "19383": "Church St/Victoria St #21",
  "19384": "McKay St/Victoria St #22",
  "19385": "Flockhart St/Victoria St #23",
  "19386": "Burnley St/Victoria St #24",
  "19387": "River Bvd/Victoria St #25",
  "19389": "Findon Cres/Barkers Rd #27",
  "19391": "High St/Barkers Rd #29",
  "19393": "Stevenson St/High St #31",
  "19394": "Kew Junction/High St #32",
  "19395": "Kew Shopping Centre/High St #33",
  "19396": "QPO/Cotham Rd #34",
  "19397": "Charles St/Cotham Rd #35",
  "19398": "Glenferrie Rd/Cotham Rd #36",
  "19399": "Belmont Ave/Cotham Rd #37",
  "19400": "Marshall Ave/Cotham Rd #38",
  "19401": "Florence Ave/Cotham Rd #39",
  "19402": "St George's Hospital/Cotham Rd #40",
  "19403": "Kew Traffic School/Cotham Rd #41",
  "19404": "Burke Rd/Cotham Rd #42",
  "19405": "Deepdene Shopping Centre/Whitehorse Rd #43",
  "19406": "Deepdene Park/Whitehorse Rd #44",
  "19407": "Hardwicke St/Whitehorse Rd #45",
  "19408": "Balwyn Cinema/Whitehorse Rd #46",
  "19409": "Balwyn Rd/Whitehorse Rd #47",
  "19410": "Balwyn Shopping Centre/Whitehorse Rd #48",
  "19411": "Northcote Ave/Whitehorse Rd #49",
  "19412": "Wharton St/Whitehorse Rd #50",
  "19413": "Narrak Rd/Whitehorse Rd #51",
  "19414": "Union Rd/Whitehorse Rd #53",
  "19416": "Inglisby Rd/Whitehorse Rd #54",
  "19417": "Hood St/Whitehorse Rd #55",
  "19418": "Elgar Rd/Whitehorse Rd #56",
  "19419": "Nelson Rd/Whitehorse Rd #57",
  "19421": "Elgar Rd/Riversdale Rd #61",
  "19422": "Ferndale St/Riversdale Rd #60",
  "19423": "Alandale St/Riversdale Rd #59",
  "19424": "Wattle Park/Riversdale Rd #58",
  "19425": "Glendale St/Riversdale Rd #57",
  "19426": "Warrigal Rd/Riversdale Rd #56",
  "19427": "Union Rd/Riversdale Rd #55",
  "19428": "Through Rd/Riversdale Rd #54",
  "19429": "Essex Rd/Riversdale Rd #53",
  "19430": "Lockhart St/Riversdale Rd #52",
  "19431": "Highfield Rd/Riversdale Rd #51",
  "19432": "Wattle Valley Rd/Riversdale Rd #50",
  "19433": "Glyndon Rd/Riversdale Rd #49",
  "19434": "Cooloongatta Rd/Riversdale Rd #48",
  "19435": "Willow Gr/Riversdale Rd #47",
  "19436": "Riversdale Station/Riversdale Rd #46",
  "19438": "Derby St/Riversdale Rd #44",
  "19439": "Trafalgar Rd/Riversdale Rd #43",
  "19440": "Fermanagh Rd/Riversdale Rd #42",
  "19441": "Camberwell Market/Riversdale Rd #41",
  "19442": "Camberwell Junction/Riversdale Rd #40",
  "19443": "Camberwell Tram Depot/Riversdale Rd #39",
  "19444": "Hastings Rd/Riversdale Rd #38",
  "19445": "Tooronga Rd/Riversdale Rd #37",
  "19446": "Auburn Rd/Riversdale Rd #36",
  "19447": "Robinson Rd/Riversdale Rd #35",
  "19448": "Kooyongkoot Rd/Riversdale Rd #34",
  "19449": "Berkeley St/Riversdale Rd #33",
  "19450": "Glenferrie Rd/Riversdale Rd #32",
  "19451": "Fordholm Rd/Riversdale Rd #31",
  "19452": "Through St/Riversdale Rd #30",
  "19454": "Power St/Riversdale Rd #29",
  "19456": "Yarra Bvd/Swan St #18",
  "19457": "Madden Gr/Swan St #17",
  "19458": "Park Gr/Swan St #16",
  "19459": "Stawell St/Swan St #15",
  "19460": "Burnley St/Swan St #14",
  "19461": "Edinburgh St/Swan St #13",
  "19462": "Coppin St/Swan St #12",
  "19463": "Church St/Swan St #11",
  "19464": "Swan Street Shopping Centre/Swan St #10",
  "19465": "Lennox St/Swan St #9",
  "19466": "Richmond Station/Swan St #8",
  "19467": "Brewster St/Mt Alexander Rd #43",
  "19468": "Thorn St/Mt Alexander Rd #44",
  "19469": "Glass St/Mt Alexander Rd #45",
  "19470": "Mt Alexander Rd/Keilor Rd #47",
  "19471": "Service St/Keilor Rd #48",
  "19472": "Essendon North PS/Keilor Rd #49",
  "19473": "Cooper St/Keilor Rd #50",
  "19475": "Keilor Rd/Matthews Ave #53",
  "19477": "Fullarton Rd/Matthews Ave #54",
  "19478": "Cameron St/Matthews Ave #55",
  "19479": "Earl St/Matthews Ave #56",
  "19480": "Hawker St/Matthews Ave #57",
  "19481": "Marshall Rd/Matthews Ave #58",
  "19482": "Airport West/Matthews Ave #59",
  "19489": "Melbourne University/Swanston St #1",
  "19491": "Lincoln Square/Swanston St #3",
  "19492": "Queensberry St/Swanston St #4",
  "19494": "RMIT University/Swanston St #7",
  "19495": "Melbourne Central Station/Swanston St #8",
  "19497": "Bourke Street Mall/Swanston St #10",
  "19498": "City Square/Swanston St #11",
  "19499": "Federation Square/Swanston St #13",
  "19500": "Arts Precinct/St Kilda Rd #14",
  "19504": "Shrine of Remembrance/St Kilda Rd #19",
  "19528": "Toorak Rd/St Kilda Rd #22",
  "19539": "Arthur St/St Kilda Rd #23",
  "19560": "Leopold St/St Kilda Rd #24",
  "19561": "Commercial Rd/St Kilda Rd #25",
  "19562": "Moubray St/St Kilda Rd #26",
  "19563": "High St/St Kilda Rd #27",
  "19565": "Union St/St Kilda Rd #29",
  "19566": "St Kilda Junction/St Kilda Rd #30",
  "19567": "Queens Way/Queens Way #31",
  "19568": "St Kilda Junction/St Kilda Rd #30",
  "19569": "Union St/St Kilda Rd #29",
  "19572": "Beatrice St/St Kilda Rd #26",
  "19573": "Commercial Rd/St Kilda Rd #25",
  "19574": "Leopold St/St Kilda Rd #24",
  "19575": "Arthur St/St Kilda Rd #23",
  "19589": "Curzon St/Queensberry St #13",
  "19590": "North Melbourne Town Hall/Errol St #12",
  "19591": "Royal Melbourne Hospital/Flemington Rd #14",
  "19594": "Royal Childrens Hospital/Flemington Rd #19",
  "19595": "Melrose St/Flemington Rd #20",
  "19597": "Flemington Bridge Station/Flemington Rd #22",
  "19598": "Djerring Flemington Hub/Mt Alexander Rd  #23",
  "19599": "Mooltan St/Mt Alexander Rd #24",
  "19600": "Mount Alexander College/Mt Alexander Rd #25",
  "19601": "Wellington St/Mt Alexander Rd #26",
  "19602": "Essendon Tram Depot/Mt Alexander Rd #27",
  "19603": "Middle St/Mt Alexander Rd #28",
  "19604": "Warrick St/Mt Alexander Rd #29",
  "19605": "Maribyrnong Rd/Mt Alexander Rd #30",
  "19606": "Montgomery St/Mt Alexander Rd #31",
  "19608": "Moonee Ponds Junction/Pascoe Vale Rd #32",
  "19609": "Moonee Valley Civic Centre/Pascoe Vale Rd #34",
  "19623": "Queens Park/Pascoe Vale Rd #35",
  "19624": "Murray St/Pascoe Vale Rd #36",
  "19625": "Buckley St/Pascoe Vale Rd #37",
  "19626": "Fletcher St/Pascoe Vale Rd #38",
  "19627": "Hoddle St/Fletcher St #39",
  "19628": "Nicholson St/Fletcher St #40",
  "19657": "Fletcher St/Napier St #41",
  "19658": "Shamrock St/Mt Alexander Rd #42",
  "19659": "Thistle St/Mt Alexander Rd #43",
  "19660": "Thorn St/Mt Alexander Rd #44",
  "19661": "Leake St/Mt Alexander Rd #45",
  "19662": "Lincoln Rd/Mt Alexander Rd #46",
  "19663": "Mt Alexander Rd/Keilor Rd #47",
  "19664": "Service St/Keilor Rd #48",
  "19665": "Essendon North Primary School/Keilor Rd #49",
  "19666": "Cooper St/Keilor Rd #50",
  "19667": "Bradshaw St/Keilor Rd #51",
  "19669": "Matthews Ave/Keilor Rd #53A",
  "19670": "Keilor Rd/Matthews Ave #53",
  "19671": "Fullarton Rd/Matthews Ave #54",
  "19672": "Cameron St/Matthews Ave #55",
  "19673": "Earl St/Matthews Ave #56",
  "19674": "Hawker St/Matthews Ave #57",
  "19675": "Marshall Rd/Matthews Ave #58",
  "19676": "Toorak Rd/St Kilda Rd #22",
  "19679": "Shrine of Remembrance/St Kilda Rd #19",
  "19684": "Arts Precinct/St Kilda Rd #14",
  "19685": "Federation Square/Swanston St #13",
  "19686": "City Square/Swanston St #11",
  "19687": "Bourke Street Mall/Swanston St #10",
  "19689": "Melbourne Central Station/Swanston St #8",
  "19690": "Carlisle St/St Kilda Rd #35",
  "19691": "RMIT University/Swanston St #7",
  "19693": "Queensberry St/Swanston St #4",
  "19694": "Lincoln Square/Swanston St #3",
  "19696": "Melbourne University/Swanston St #1",
  "19697": "Inkerman St/St Kilda Rd #34",
  "19698": "Inkerman St/St Kilda Rd #34",
  "19699": "Murphy St/Flemington Rd #15",
  "19700": "Argyle St/St Kilda Rd #33",
  "19701": "Argyle St/St Kilda Rd #33",
  "19702": "Alma Rd/St Kilda Rd #32",
  "19703": "Alma Rd/St Kilda Rd #32",
  "19704": "Barkly St/St Kilda Rd #31",
  "19705": "Barkly St/St Kilda Rd #31",
  "19706": "Epworth Hospital/Bridge Rd #15",
  "19708": "Bosisto St/Bridge Rd #17",
  "19709": "Church St/Bridge Rd #18",
  "19710": "Richmond Town Hall/Bridge Rd #19",
  "19711": "Coppin St/Bridge Rd #20",
  "19712": "Burnley St/Bridge Rd #21",
  "19713": "Yarra Bvd/Bridge Rd #22",
  "19714": "Yarra Bvd/Bridge Rd #22",
  "19715": "Burnley St/Bridge Rd #21",
  "19716": "Coppin St/Bridge Rd #20",
  "19717": "Richmond Town Hall/Bridge Rd #19",
  "19718": "Church St/Bridge Rd #18",
  "19719": "Waltham St/Bridge Rd #17",
  "19721": "Southbank Tram Depot/Light Rail #125A",
  "19722": "Montague St/Light Rail #126",
  "19723": "North Port Station/Light Rail #127",
  "19724": "Graham St/Light Rail #128",
  "19725": "Beacon Cove/Light Rail #129",
  "19726": "Lansdowne St/Victoria Pde #13",
  "19728": "Smith St/Victoria Pde #15",
  "19729": "Wellington St/Victoria Pde #16",
  "19731": "Hoddle St/Victoria Pde #18",
  "19732": "North Richmond Railway Station/Victoria St #19",
  "19733": "Lennox St/Victoria St #20",
  "19734": "Epworth Hospital/Bridge Rd #15",
  "19735": "McKay St/Victoria St #22",
  "19736": "Leslie St/Victoria St #23",
  "19737": "Burnley St/Victoria St #24",
  "19738": "River Bvd/Victoria St #25",
  "19740": "Findon St/Barkers Rd #27",
  "19742": "Barkers Rd/High St #29",
  "19744": "Stevenson St/High St #31",
  "19745": "Kew Junction/High St #32",
  "19746": "High St/Cotham Rd #34",
  "19747": "Charles St/Cotham Rd #35",
  "19748": "Glenferrie Rd/Cotham Rd #36",
  "19749": "Belmont Ave/Cotham Rd #37",
  "19750": "Marshall Ave/Cotham Rd #38",
  "19751": "Thomas St/Cotham Rd #39",
  "19752": "St George's Hospital/Cotham Rd #40",
  "19753": "Kew Traffic School/Cotham Rd #41",
  "19754": "Kooyongkoot Rd/Riversdale Rd #34",
  "19755": "Robinson Rd/Riversdale Rd #35",
  "19756": "Auburn Rd/Riversdale Rd #36",
  "19757": "Tooronga Rd/Riversdale Rd #37",
  "19758": "Hastings Rd/Riversdale Rd #38",
  "19759": "Camberwell Tram Depot/Riversdale Rd #39",
  "19760": "Camberwell Junction/Riversdale Rd #40",
  "19761": "Fermanagh Rd/Riversdale Rd #42",
  "19762": "Trafalgar Rd/Riversdale Rd #43",
  "19763": "Derby St/Riversdale Rd #44",
  "19764": "Riversdale Station/Riversdale Rd #46",
  "19765": "Willow Gr/Riversdale Rd #47",
  "19766": "Cooloongatta Rd/Riversdale Rd #48",
  "19767": "Glyndon Rd/Riversdale Rd #49",
  "19768": "Wattle Valley Rd/Riversdale Rd #50",
  "19769": "Highfield Rd/Riversdale Rd #51",
  "19770": "Lockhart St/Riversdale Rd #52",
  "19771": "Essex Rd/Riversdale Rd #53",
  "19772": "Through Rd/Riversdale Rd #54",
  "19773": "Union Rd/Riversdale Rd #55",
  "19774": "Warrigal Rd/Riversdale Rd #56",
  "19775": "Glendale St/Riversdale Rd #57",
  "19776": "Wattle Park/Riversdale Rd #58",
  "19777": "Alandale St/Riversdale Rd #59",
  "19778": "Burke Rd/Whitehorse Rd #42",
  "19779": "Ferndale St/Riversdale Rd #60",
  "19781": "Box Hill Central/Whitehorse Rd #58",
  "19782": "Nelson Rd/Whitehorse Rd #57",
  "19783": "Elgar Rd/Whitehorse Rd #56",
  "19784": "Hood St/Whitehorse Rd #55",
  "19785": "Inglisby Rd/Whitehorse Rd #54",
  "19786": "Union Rd/Whitehorse Rd #53",
  "20482": "Murphy St/Flemington Rd #15",
  "20490": "Flemington Rd/Peel St #12",
  "20491": "Flemington Rd/Peel St #12",
  "20492": "Queensberry St/Peel St #11",
  "20493": "Queensberry St/Peel St #11",
  "20494": "City Rd/Light Rail #126",
  "20495": "City Rd/Light Rail #126",
  "20496": "South Melbourne Station/Light Rail #127",
  "20497": "South Melbourne Station/Light Rail #127",
  "20498": "Albert Park Station/Light Rail #128",
  "20499": "Albert Park Station/Light Rail #128",
  "20500": "Melbourne Sports and Aquatic Centre/Light Rail #129",
  "20501": "Melbourne Sports and Aquatic Centre/Light Rail #129",
  "20502": "Middle Park Station/Light Rail #130",
  "20503": "Middle Park Station/Light Rail #130",
  "20504": "Fraser St/Light Rail #131",
  "20505": "Fraser St/Light Rail #131",
  "20506": "St Kilda Station/Fitzroy St #132",
  "20507": "St Kilda Station/Fitzroy St #132",
  "20508": "Canterbury Rd/Fitzroy St #133",
  "20509": "Canterbury Rd/Fitzroy St #133",
  "20510": "Park St/Fitzroy St #134",
  "20511": "Park St/Fitzroy St #134",
  "20512": "Acland St/Fitzroy St #135",
  "20513": "Jacka Bvd/Fitzroy St #135",
  "20514": "Alfred Square/The Esplanade #136",
  "20515": "Alfred Square/The Esplanade #136",
  "20518": "Luna Park/The Esplanade #138",
  "20519": "Luna Park/The Esplanade #138",
  "20520": "Belford St/Acland St #139",
  "20522": "Belford St/Acland St #139",
  "20523": "Hawthorn Rd/Dandenong Rd #48",
  "20524": "Hawthorn Rd/Dandenong Rd #48",
  "20525": "Dandenong Rd/Glenferrie Rd #52",
  "20526": "Malvern Railway Station/Glenferrie Rd #53",
  "20527": "Malvern Railway Station/Glenferrie Rd #53",
  "20528": "Wattletree Rd/Glenferrie Rd #54",
  "20529": "Wattletree Rd/Glenferrie Rd #54",
  "20530": "Llaneast St/Glenferrie Rd #55",
  "20531": "Edsall St/Glenferrie Rd #55",
  "20532": "Malvern Tram Depot/Glenferrie Rd #56",
  "20533": "Malvern Tram Depot/Glenferrie Rd #56",
  "20534": "High St/Glenferrie Rd #57",
  "20535": "High St/Glenferrie Rd #57",
  "20536": "Bell St/Glenferrie Rd #58",
  "20537": "Sorrett Ave/Glenferrie Rd #58",
  "20538": "Malvern Rd/Glenferrie Rd #59",
  "20539": "Malvern Rd/Glenferrie Rd #59",
  "20540": "Stonnington Pl/Glenferrie Rd #60",
  "20541": "Stonnington Pl/Glenferrie Rd #60",
  "20542": "Moorakyne Ave/Glenferrie Rd #61",
  "20543": "Moorakyne Ave/Glenferrie Rd #61",
  "20544": "Mayfield Ave/Glenferrie Rd #62",
  "20545": "Mayfield Ave/Glenferrie Rd #62",
  "20546": "Toorak Rd/Glenferrie Rd #63",
  "20547": "Toorak Rd/Glenferrie Rd #63",
  "20548": "Mernda Rd/Glenferrie Rd #64",
  "20549": "Power St/Glenferrie Rd #64",
  "20550": "Warra St/Glenferrie Rd #65",
  "20551": "Kooyong Railway Station/Glenferrie Rd #65",
  "20552": "Kooyong Tennis Centre/Glenferrie Rd #66",
  "20553": "Vision Australia/Glenferrie Rd #66",
  "20554": "Gardiner Rd/Glenferrie Rd #67",
  "20555": "Gardiner Rd/Glenferrie Rd #67",
  "20556": "Callantina Rd/Glenferrie Rd #68",
  "20557": "Callantina Rd/Glenferrie Rd #68",
  "20558": "South St/Glenferrie Rd #69",
  "20559": "South St/Glenferrie Rd #69",
  "20560": "Riversdale Rd/Glenferrie Rd #70",
  "20561": "Riversdale Rd/Glenferrie Rd #70",
  "20562": "Urquhart St/Glenferrie Rd #71",
  "20563": "Urquhart St/Glenferrie Rd #71",
  "20564": "Manningtree Rd/Glenferrie Rd #72",
  "20565": "Manningtree Rd/Glenferrie Rd #72",
  "20566": "Burwood Rd/Glenferrie Rd #73",
  "20567": "Burwood Rd/Glenferrie Rd #73",
  "20569": "Glenferrie Station/Glenferrie Rd #74",
  "20570": "Chrystobel Cres/Glenferrie Rd #75",
  "20571": "Liddiard St/Glenferrie Rd #75",
  "20572": "Johnson St/Glenferrie Rd #76",
  "20573": "Johnson St/Glenferrie Rd #76",
  "20584": "Barkers Rd/Glenferrie Rd #77",
  "20589": "Barkers Rd/Glenferrie Rd #77",
  "20590": "Fitzwilliam St/Glenferrie Rd #78",
  "20591": "Fitzwilliam St/Glenferrie Rd #78",
  "20592": "Wellington St/Glenferrie Rd #79",
  "20593": "Wellington St/Glenferrie Rd #79",
  "20595": "Cotham Rd/Glenferrie Rd #80",
  "20597": "Chapel St/Carlisle St #37",
  "20598": "Balaclava Station/Carlisle St #38",
  "20599": "Carlisle Ave/Carlisle St #39",
  "20647": "Hotham St/Balaclava Rd #40",
  "20648": "Vadlure Ave/Balaclava Rd #41",
  "20774": "Hoffmans Rd/Keilor Rd #52",
  "20775": "Buckley St/Pascoe Vale Rd #37",
  "20778": "St James Park/Burwood Rd #25",
  "20779": "St James Park/Burwood Rd #25",
  "20780": "Hawthorn Railway Station/Burwood Rd #26",
  "20781": "Hawthorn Railway Station/Burwood Rd #26",
  "20782": "Burwood Rd/Power St #27",
  "20783": "Power St/Burwood Rd #27",
  "20784": "Wattle Rd/Power St #28",
  "20785": "Wattle Rd/Power St #28",
  "20895": "Burke Rd/Doncaster Rd #44",
  "20979": "Bourke St/Spring St #0",
  "20980": "Normanby Ave/High St #38",
  "20981": "Docklands Stadium/La Trobe St  #D1",
  "21042": "Allan Rd/Balaclava Rd #42",
  "21057": "Orrong Rd/Balaclava Rd #43",
  "21058": "Otira Rd/Balaclava Rd #44",
  "21059": "Kent Gr/Balaclava Rd #45",
  "21060": "Kooyong Rd/Balaclava Rd #46",
  "21061": "Burke Rd/Camberwell Rd #41",
  "21062": "Camberwell Primary School/Camberwell Rd #42",
  "21063": "Camberwell Primary School/Camberwell Rd #42",
  "21064": "Camberwell Civic Centre/Camberwell Rd #43",
  "21065": "Camberwell Civic Centre/Camberwell Rd #43",
  "21066": "Trafalgar Rd/Camberwell Rd #44",
  "21067": "Trafalgar Rd/Camberwell Rd #44",
  "21068": "Bowen St/Camberwell Rd #45",
  "21069": "Bowen St/Camberwell Rd #45",
  "21070": "Christowel St/Camberwell Rd #46",
  "21071": "Acheron Ave/Camberwell Rd #46",
  "21072": "Maple Cres/Camberwell Rd #47",
  "21073": "Orange Gr/Camberwell Rd #47",
  "21074": "Orrong Cres/Camberwell Rd #48",
  "21075": "Glen Iris Rd/Camberwell Rd #48",
  "21076": "Tyrone St/Camberwell Rd #49",
  "21077": "Wilson Gr/Camberwell Rd #49",
  "21078": "Fordham Gardens/Camberwell Rd #50",
  "21079": "Smith Rd/Camberwell Rd #50",
  "21080": "Toorak Rd/Camberwell Rd #51",
  "21081": "Summerhill Rd/Toorak Rd #52",
  "21082": "Summerhill Rd/Toorak Rd #52",
  "21083": "Highfield Rd/Toorak Rd #53",
  "21084": "Lithgow St/Toorak Rd #53",
  "21085": "Oberwyl Rd/Toorak Rd #54",
  "21086": "Grandview Ave/Toorak Rd #54",
  "21087": "Through Rd/Toorak Rd #55",
  "21088": "Beryl St/Toorak Rd #55",
  "21089": "Barkly St/Toorak Rd #56",
  "21090": "Alfred Rd/Toorak Rd #56",
  "21091": "Fairview Ave/Toorak Rd #57",
  "21092": "Queens Pde/Toorak Rd #57",
  "21093": "Warrigal Rd/Burwood Hwy #58",
  "21094": "Warrigal Rd/Burwood Hwy #58",
  "21095": "Somers St/Burwood Hwy #59",
  "21096": "Gilmour St/Burwood Hwy #59",
  "21097": "Roslyn St/Burwood Hwy #60",
  "21098": "Millicent St/Burwood Hwy #60",
  "21099": "Presbyterian Ladies College/Burwood Hwy #61",
  "21100": "Presbyterian Ladies College/Burwood Hwy #61",
  "21101": "Elgar Rd/Burwood Hwy #62",
  "21102": "Elgar Rd/Burwood Hwy #62",
  "21103": "Deakin University/Burwood Hwy #63",
  "21104": "Deakin University/Burwood Hwy #63",
  "21105": "Station St/Burwood Hwy #64",
  "21106": "Station St/Burwood Hwy #64",
  "21107": "Starling St/Burwood Hwy #65",
  "21108": "Starling St/Burwood Hwy #65",
  "21109": "Middleborough Rd/Burwood Hwy #66",
  "21110": "Middleborough Rd/Burwood Hwy #66",
  "21111": "Old Burwood Rd/Burwood Hwy #67",
  "21112": "Old Burwood Rd/Burwood Hwy #67",
  "21113": "Benwerrin Reserve/Burwood Hwy #68",
  "21114": "Benwerrin Reserve/Burwood Hwy #68",
  "21115": "Keats St/Burwood Hwy #69",
  "21116": "Highview Gr/Burwood Hwy #69",
  "21117": "Blackburn Rd/Burwood Hwy #70",
  "21118": "Blackburn Rd/Burwood Hwy #70",
  "21119": "Sevenoaks Rd/Burwood Hwy #71",
  "21120": "Sevenoaks Rd/Burwood Hwy #71",
  "21121": "Lakeside Dr/Burwood Hwy #72",
  "21122": "Lakeside Dr/Burwood Hwy #72",
  "21123": "Springvale Rd/Burwood Hwy #73",
  "21124": "Springvale Rd/Burwood Hwy #73",
  "21125": "Stanley Rd/Burwood Hwy #74",
  "21126": "Stanley Rd/Burwood Hwy #74",
  "21127": "Vermont South Shopping Centre/Burwood Hwy #75",
  "21196": "Bradshaw St/Keilor Rd #51",
  "21231": "Spencer St/Flinders St #1",
  "21232": "Spencer St/Flinders St #1",
  "21233": "Melbourne Aquarium/Flinders St #2",
  "21234": "Melbourne Aquarium/Flinders St #2",
  "21961": "Moore St/Sydney Rd #29",
  "21962": "Barkly Square/Sydney Rd #20",
  "21963": "Carlisle St/St Kilda Rd #35",
  "21964": "Camberwell Junction/Camberwell Rd #40",
  "21966": "Church St/Victoria St #21",
  "22100": "Smith St/Victoria Pde #15",
  "22109": "St Kilda Rd/Fitzroy St #131",
  "22110": "St Kilda Rd/Fitzroy St #131",
  "22111": "Princes St/Fitzroy St #132",
  "22112": "Princes St/Fitzroy St #132",
  "22152": "Exhibition St/Collins St #7",
  "22153": "Exhibition St/Collins St #7",
  "22305": "Treadwell Rd/Keilor Rd #52",
  "22320": "Wests Rd/Cordite Ave #48",
  "22559": "Scotchmer St/St Georges Rd #22",
  "22560": "Hawthorn Bridge/Bridge Rd #23",
  "22561": "Hawthorn Bridge/Bridge Rd #23",
  "22612": "City Rd/Kings Way #116",
  "22903": "William Barak Bridge/Melbourne Park #7A",
  "22904": "William Barak Bridge/Melbourne Park #7A",
  "43472": "Southern Cross Station/Collins St #D14",
  "43473": "Batman's Hill/Collins St #D15",
  "43474": "Merchant St/Collins St #D17",
  "43475": "Harbour Esp/Collins St #D16",
  "43476": "Batman's Hill/Collins St #D15",
  "43477": "Southern Cross Station/Collins St #D14",
  "43480": "Harbour Esp/Collins St #D16",
  "46517": "Hawthorn Rd/Dandenong Rd #48",
  "46823": "Raleigh Rd/Wests Rd #48",
  "46831": "ANZAC Station/St Kilda Rd #20",
  "46849": "ANZAC Station/St Kilda Rd #20",
  "46863": "Spencer St/La Trobe St #1",
  "46864": "Spencer St/La Trobe St #1",
  "46865": "Flagstaff Station/La Trobe St  #3",
  "46866": "Melbourne Central Station/La Trobe St  #5",
  "46867": "Exhibition St/La Trobe St #8",
  "46868": "Exhibition St/La Trobe St #8",
  "46869": "Tyler St/Plenty Rd #52",
  "46871": "St Vincent Plaza/Victoria St  #12",
  "46872": "Bourke St/Collins St #D18",
  "46873": "Merchant St/Collins St #D17",
  "46874": "Waterfront City/Docklands Dr #D11",
  "46875": "Vermont South Shopping Centre/Burwood Hwy #75",
  "46876": "Brighton Rd/Chapel St #36",
  "46877": "RMIT/Plenty Rd #71",
  "46878": "Box Hill Central/Whitehorse Rd #58",
  "46879": "Lorne St/St Kilda Rd #27",
  "46880": "Grant St-Police Memorial/St Kilda Rd #17",
  "46881": "Grant St-Police Memorial/St Kilda Rd #17",
  "46882": "Glenferrie Railway Station/Glenferrie Rd #74",
  "47493": "Bourke St/Collins St #D18",
  "49275": "Woodlands Ave/Melville Rd #41",
  "49276": "South Daly St/Dawson St #33",
  "49277": "Heller St/Grantham St #29",
  "49278": "Jacobs Reserve/Melville Rd #38",
  "49279": "Woodlands Ave/Melville Rd #41",
  "49280": "Reynard St/Melville Rd #42",
  "49999": "Toorak Rd/St Kilda Rd #22",
  "52112": "Fawkner Park/Toorak Rd #123",
  "52113": "Fawkner Park/Toorak Rd #123"
}